{"stats":{"minecraft:mined":{"minecraft:oak_sapling":2,"minecraft:oak_log":31,"minecraft:tall_grass":1,"minecraft:cobblestone":1,"minecraft:stone":14,"minecraft:oak_leaves":7},"minecraft:picked_up":{"minecraft:stick":2,"minecraft:cooked_beef":16,"minecraft:clownfish":2,"minecraft:salmon":3,"minecraft:wooden_pickaxe":2,"minecraft:oak_log":31,"minecraft:stone_sword":1,"minecraft:apple":1,"minecraft:stone_axe":1,"minecraft:oak_boat":3,"minecraft:gold_ingot":1,"minecraft:oak_sapling":6,"minecraft:cod":2,"minecraft:iron_boots":2,"minecraft:cobblestone":33,"minecraft:egg":1},"minecraft:dropped":{"minecraft:cooked_beef":1,"minecraft:gold_ingot":1,"minecraft:cod":1},"minecraft:killed_by":{"minecraft:player":1,"minecraft:drowned":1},"minecraft:crafted":{"minecraft:oak_boat":3,"minecraft:oak_planks":36,"minecraft:crafting_table":2,"minecraft:stick":8,"minecraft:wooden_pickaxe":1,"minecraft:stone_pickaxe":1,"minecraft:stone_sword":1,"minecraft:stone_axe":1},"minecraft:used":{"minecraft:apple":1,"minecraft:wooden_pickaxe":15,"minecraft:stone_axe":18,"minecraft:cobblestone":1,"minecraft:crafting_table":2,"minecraft:oak_sapling":4,"minecraft:cod":1,"minecraft:oak_boat":3,"minecraft:egg":1,"minecraft:cooked_beef":9},"minecraft:custom":{"minecraft:time_since_rest":1685,"minecraft:sprint_one_cm":94227,"minecraft:damage_taken":1896,"minecraft:walk_one_cm":188231,"minecraft:drop":3,"minecraft:dive_one_cm":316017,"minecraft:damage_dealt":168,"minecraft:swim_one_cm":29235,"minecraft:interact_with_crafting_table":5,"minecraft:fly_one_cm":48499,"minecraft:open_chest":7,"minecraft:crouch_one_cm":2489,"minecraft:play_one_minute":73074,"minecraft:deaths":4,"minecraft:sneak_time":3262,"minecraft:boat_one_cm":422769,"minecraft:jump":576,"minecraft:leave_game":6,"minecraft:time_since_death":1654,"minecraft:sleep_in_bed":1,"minecraft:fall_one_cm":15471}},"DataVersion":1481}